{"SubTexture":[{"frameWidth":222,"y":843,"frameHeight":421,"width":216,"frameX":-6,"height":418,"name":"мега_гига_стойка_0","frameY":-1,"x":873},{"frameWidth":222,"y":844,"frameHeight":421,"width":216,"frameX":-6,"height":418,"name":"мега_гига_стойка_1","frameY":-1,"x":1},{"frameWidth":222,"y":843,"frameHeight":421,"width":216,"frameX":-5,"height":418,"name":"мега_гига_стойка_2","frameY":-1,"x":1746},{"frameWidth":222,"y":421,"frameHeight":421,"width":216,"frameX":-5,"height":419,"name":"мега_гига_стойка_3","frameY":0,"x":1531},{"frameWidth":222,"y":424,"frameHeight":421,"width":216,"frameX":-4,"height":419,"name":"мега_гига_стойка_4","frameY":0,"x":219},{"frameWidth":222,"y":844,"frameHeight":421,"width":216,"frameX":-4,"height":418,"name":"мега_гига_стойка_5","frameY":0,"x":1309},{"frameWidth":222,"y":422,"frameHeight":421,"width":216,"frameX":-4,"height":419,"name":"мега_гига_стойка_6","frameY":0,"x":1749},{"frameWidth":222,"y":422,"frameHeight":421,"width":216,"frameX":-3,"height":419,"name":"мега_гига_стойка_7","frameY":0,"x":656},{"frameWidth":222,"y":1,"frameHeight":421,"width":216,"frameX":-3,"height":419,"name":"мега_гига_стойка_8","frameY":0,"x":1750},{"frameWidth":222,"y":843,"frameHeight":421,"width":216,"frameX":-2,"height":419,"name":"мега_гига_стойка_9","frameY":0,"x":437},{"frameWidth":222,"y":423,"frameHeight":421,"width":216,"frameX":-2,"height":419,"name":"мега_гига_стойка_10","frameY":0,"x":1310},{"frameWidth":222,"y":423,"frameHeight":421,"width":216,"frameX":-2,"height":419,"name":"мега_гига_стойка_11","frameY":0,"x":1},{"frameWidth":222,"y":422,"frameHeight":421,"width":216,"frameX":-1,"height":419,"name":"мега_гига_стойка_12","frameY":0,"x":438},{"frameWidth":222,"y":423,"frameHeight":421,"width":216,"frameX":-1,"height":419,"name":"мега_гига_стойка_13","frameY":0,"x":1092},{"frameWidth":222,"y":1,"frameHeight":421,"width":217,"frameX":0,"height":419,"name":"мега_гига_стойка_14","frameY":0,"x":876},{"frameWidth":222,"y":1,"frameHeight":421,"width":217,"frameX":-1,"height":419,"name":"мега_гига_стойка_15","frameY":0,"x":438},{"frameWidth":222,"y":1,"frameHeight":421,"width":217,"frameX":-1,"height":420,"name":"мега_гига_стойка_16","frameY":0,"x":1},{"frameWidth":222,"y":1,"frameHeight":421,"width":216,"frameX":-2,"height":420,"name":"мега_гига_стойка_17","frameY":0,"x":1095},{"frameWidth":222,"y":1,"frameHeight":421,"width":216,"frameX":-2,"height":421,"name":"мега_гига_стойка_18","frameY":0,"x":220},{"frameWidth":222,"y":1,"frameHeight":421,"width":216,"frameX":-3,"height":420,"name":"мега_гига_стойка_19","frameY":0,"x":1313},{"frameWidth":222,"y":1,"frameHeight":421,"width":217,"frameX":-3,"height":419,"name":"мега_гига_стойка_20","frameY":0,"x":657},{"frameWidth":222,"y":422,"frameHeight":421,"width":216,"frameX":-4,"height":419,"name":"мега_гига_стойка_21","frameY":0,"x":874},{"frameWidth":222,"y":843,"frameHeight":421,"width":216,"frameX":-4,"height":419,"name":"мега_гига_стойка_22","frameY":0,"x":655},{"frameWidth":222,"y":842,"frameHeight":421,"width":216,"frameX":-5,"height":419,"name":"мега_гига_стойка_23","frameY":0,"x":1528},{"frameWidth":222,"y":844,"frameHeight":421,"width":216,"frameX":-5,"height":418,"name":"мега_гига_стойка_24","frameY":-1,"x":1091},{"frameWidth":222,"y":1,"frameHeight":421,"width":217,"frameX":-5,"height":418,"name":"мега_гига_стойка_25","frameY":-1,"x":1531}],"name":"pizdec7_tex","imagePath":"Armature_tex.png"}